dojo_pong/__init__.py
dojo_pong/ball.py
dojo_pong/main.py
dojo_pong/paddle.py
dojo_pong/scoreboard.py
dojo_pong_pkg_ferromauro-0.0.1.dist-info/LICENSE
dojo_pong_pkg_ferromauro-0.0.1.dist-info/METADATA
dojo_pong_pkg_ferromauro-0.0.1.dist-info/WHEEL
dojo_pong_pkg_ferromauro-0.0.1.dist-info/top_level.txt
dojo_pong_pkg_ferromauro-0.0.1.dist-info/RECORD
