Metadata-Version: 2.1
Name: dojo-pong-pkg-ferromauro
Version: 0.0.1
Summary: Game tutorial for elearning course on www.digitaldojo.it
Home-page: https://github.com/ferromauro/dojo-pong
Author: Mauro Ferro
Author-email: postmaster@ferromauro.it
License: UNKNOWN
Platform: UNKNOWN
Classifier: Programming Language :: Python :: 3
Classifier: License :: OSI Approved :: MIT License
Classifier: Operating System :: OS Independent
Requires-Python: >=3.6
